MANIFEST.in
README.md
setup.cfg
setup.py
amsimp/__init__.py
amsimp/forecasting.py
amsimp/preprocessing.py
amsimp.egg-info/PKG-INFO
amsimp.egg-info/SOURCES.txt
amsimp.egg-info/dependency_links.txt
amsimp.egg-info/not-zip-safe
amsimp.egg-info/top_level.txt
amsimp/model/global_forecast_model.h5
amsimp/model/mean.npy
amsimp/model/std.npy