Metadata-Version: 2.1
Name: amsimp
Version: 0.6.0
Summary: Numerical Weather Prediction using Machine Learning
Home-page: https://amsimp.com
Author: AMSIMP
Author-email: support@amsimp.com
License: UNKNOWN
Download-URL: https://github.com/amsimp/amsimp.git
Platform: UNKNOWN
Classifier: Programming Language :: Python :: 3
Classifier: License :: OSI Approved :: MIT License
Classifier: Operating System :: MacOS :: MacOS X
Classifier: Operating System :: POSIX :: Linux
Classifier: Programming Language :: Cython
Classifier: Programming Language :: Python :: 3.7
Classifier: Topic :: Scientific/Engineering
Classifier: Topic :: Scientific/Engineering :: Atmospheric Science
Classifier: Topic :: Scientific/Engineering :: Visualization
Classifier: Topic :: Scientific/Engineering :: Physics
